afxdl/__init__.py
afxdl/download.py
afxdl/main.py
afxdl/models.py
afxdl/parse.py
afxdl/py.typed
afxdl-1.0.0.dist-info/METADATA
afxdl-1.0.0.dist-info/WHEEL
afxdl-1.0.0.dist-info/entry_points.txt
afxdl-1.0.0.dist-info/licenses/LICENSE
afxdl-1.0.0.dist-info/RECORD
