Metadata-Version: 2.4
Name: afxdl
Version: 1.0.0
Summary: Download audio from aphextwin.warp.net
Project-URL: Repository, https://github.com/eggplants/afxdl
Author-email: eggplants <w10776e8w@yahoo.co.jp>
License: MIT
License-File: LICENSE
Keywords: aphextwin,cli,commandline-tool,downloader,id3-tag,mp3,warp
Classifier: Development Status :: 4 - Beta
Classifier: Environment :: Console
Classifier: Operating System :: OS Independent
Classifier: Programming Language :: Python :: 3 :: Only
Classifier: Programming Language :: Python :: 3.12
Classifier: Programming Language :: Python :: 3.13
Classifier: Programming Language :: Python :: 3.14
Classifier: Topic :: Multimedia :: Sound/Audio
Classifier: Typing :: Typed
Requires-Python: <4,>=3.12
Requires-Dist: beautifulsoup4<5,>=4.12.3
Requires-Dist: mutagen<2,>=1.47
Requires-Dist: pydantic<3,>=2.10.5
Requires-Dist: requests<3,>=2.32.3
